sample/__init__.py
sample/core.py
sample/helpers.py
sample_jojo-0.1.0.dist-info/DESCRIPTION.rst
sample_jojo-0.1.0.dist-info/METADATA
sample_jojo-0.1.0.dist-info/RECORD
sample_jojo-0.1.0.dist-info/WHEEL
sample_jojo-0.1.0.dist-info/metadata.json
sample_jojo-0.1.0.dist-info/top_level.txt
